sampah/__init__.py
sampah/cli.py
sampah/web.py
sampah/static/style.css
sampah/templates/index.html
sampah-0.1.2.dist-info/METADATA
sampah-0.1.2.dist-info/WHEEL
sampah-0.1.2.dist-info/entry_points.txt
sampah-0.1.2.dist-info/top_level.txt
sampah-0.1.2.dist-info/RECORD
