Metadata-Version: 2.4
Name: sampah
Version: 0.1.2
Summary: Short description of your package
Home-page: https://github.com/aiamirul/SAMPAH
Author: Amirul Sadikin
Author-email: ai.amirul.sadikin@gmail.com
Classifier: Programming Language :: Python :: 3
Classifier: License :: OSI Approved :: MIT License
Requires-Python: >=3.6
Requires-Dist: flask
Dynamic: author
Dynamic: author-email
Dynamic: classifier
Dynamic: description
Dynamic: description-content-type
Dynamic: home-page
Dynamic: requires-dist
Dynamic: requires-python
Dynamic: summary
